count_distinct-0.2.4.dist-info/METADATA
count_distinct-0.2.4.dist-info/WHEEL
count_distinct-0.2.4.dist-info/licenses/LICENSE.md
count_distinct/__init__.py
count_distinct/count_distinct.cpython-313t-darwin.so
count_distinct-0.2.4.dist-info/RECORD
