Metadata-Version: 2.4
Name: count_distinct
Version: 0.2.4
Classifier: Programming Language :: Python
Classifier: Programming Language :: Python :: 3.10
Classifier: Programming Language :: Python :: 3.11
Classifier: Programming Language :: Python :: 3.12
Classifier: Programming Language :: Python :: 3.13
Classifier: Programming Language :: Python :: 3.14
Classifier: Development Status :: 5 - Production/Stable
Classifier: Intended Audience :: Science/Research
Classifier: License :: OSI Approved :: Blue Oak Model License (BlueOak-1.0.0)
Classifier: Operating System :: OS Independent
License-File: LICENSE.md
Summary: Use the CVM algorithm to quickly estimate the number of distinct elements in a stream
Keywords: cvm,count-distinct,estimation
Author-email: Stephan Hügel <urschrei@gmail.com>
Requires-Python: >=3.10
Project-URL: Repository, https://github.com/urschrei/cvmcount_py
Project-URL: Tracker, https://github.com/urschrei/cvmcount_py/issues
